edq_pacai-2.0.0.dist-info/licenses/LICENSE
edq_pacai-2.0.0.dist-info/licenses/LICENSE-code
edq_pacai-2.0.0.dist-info/licenses/LICENSE-noncode
pacai/__init__.py
pacai/agents/__init__.py
pacai/agents/cheating.py
pacai/agents/dummy.py
pacai/agents/gowest.py
pacai/agents/greedy.py
pacai/agents/leftturn.py
pacai/agents/mdp.py
pacai/agents/minimax.py
pacai/agents/random.py
pacai/agents/scripted.py
pacai/agents/searchproblem.py
pacai/agents/testing.py
pacai/agents/userinput.py
pacai/capture/__init__.py
pacai/capture/__main__.py
pacai/capture/agents.py
pacai/capture/bin.py
pacai/capture/board.py
pacai/capture/game.py
pacai/capture/gamestate.py
pacai/capture/team.py
pacai/core/__init__.py
pacai/core/action.py
pacai/core/agent.py
pacai/core/agentaction.py
pacai/core/agentinfo.py
pacai/core/board.py
pacai/core/board_test.py
pacai/core/features.py
pacai/core/font.py
pacai/core/game.py
pacai/core/gamestate.py
pacai/core/gamestate_test.py
pacai/core/log.py
pacai/core/mdp.py
pacai/core/search.py
pacai/core/spritesheet.py
pacai/core/spritesheet_test.py
pacai/core/ticket.py
pacai/core/ticket_test.py
pacai/core/ui.py
pacai/core/isolation/__init__.py
pacai/core/isolation/isolator.py
pacai/core/isolation/level.py
pacai/core/isolation/none.py
pacai/core/isolation/process.py
pacai/eightpuzzle/__init__.py
pacai/eightpuzzle/__main__.py
pacai/eightpuzzle/bin.py
pacai/eightpuzzle/board.py
pacai/eightpuzzle/problem.py
pacai/gridworld/__init__.py
pacai/gridworld/__main__.py
pacai/gridworld/bin.py
pacai/gridworld/board.py
pacai/gridworld/game.py
pacai/gridworld/gamestate.py
pacai/gridworld/mdp.py
pacai/pacman/__init__.py
pacai/pacman/__main__.py
pacai/pacman/bin.py
pacai/pacman/board.py
pacai/pacman/features.py
pacai/pacman/game.py
pacai/pacman/gamestate.py
pacai/pacman/textui.py
pacai/resources/__init__.py
pacai/resources/boards/__init__.py
pacai/resources/boards/capture-alley.board
pacai/resources/boards/capture-blox.board
pacai/resources/boards/capture-crowded.board
pacai/resources/boards/capture-default.board
pacai/resources/boards/capture-distant.board
pacai/resources/boards/capture-fast.board
edq_pacai-2.0.0.dist-info/METADATA
edq_pacai-2.0.0.dist-info/WHEEL
edq_pacai-2.0.0.dist-info/top_level.txt
edq_pacai-2.0.0.dist-info/RECORD
