Metadata-Version: 2.4
Name: edq-pacai
Version: 2.0.0
Summary: An AI educational project disguised as Pac-Man.
Author-email: Eriq Augustine <eriq@edulinq.org>, Connor Pryor <cfpryor@ucsc.edu>, LINQS <linqs.edu@gmail.com>
Project-URL: Homepage, https://github.com/linqs/pacman
Project-URL: Repository, https://github.com/linqs/pacman
Keywords: AI,Artificial Intelligence,Education,Teaching
Classifier: Intended Audience :: Science/Research
Classifier: Intended Audience :: Education
Classifier: Operating System :: OS Independent
Classifier: Programming Language :: Python :: 3.10
Classifier: Topic :: Education
Classifier: Topic :: Scientific/Engineering :: Artificial Intelligence
Requires-Python: >=3.10
License-File: LICENSE
License-File: LICENSE-code
License-File: LICENSE-noncode
Requires-Dist: Pillow>=8.3.2
Requires-Dist: edq-utils>=0.0.4
Requires-Dist: json5>=0.9.14
Provides-Extra: dev
Requires-Dist: mypy>=1.15; extra == "dev"
Requires-Dist: pdoc>=14.7.0; extra == "dev"
Requires-Dist: pylint; extra == "dev"
Requires-Dist: twine; extra == "dev"
Requires-Dist: vermin; extra == "dev"
Dynamic: license-file
